aiozello/__init__.py
aiozello/auth.py
aiozello-0.1.0.dist-info/LICENSE
aiozello-0.1.0.dist-info/METADATA
aiozello-0.1.0.dist-info/WHEEL
aiozello-0.1.0.dist-info/RECORD
